mypackage1995/__init__.py
mypackage1995/main.py
mypackage1995/main2.py
mypackage1995-0.0.4.dist-info/LICENSE
mypackage1995-0.0.4.dist-info/METADATA
mypackage1995-0.0.4.dist-info/WHEEL
mypackage1995-0.0.4.dist-info/top_level.txt
mypackage1995-0.0.4.dist-info/RECORD
