Metadata-Version: 2.1
Name: mypackage1995
Version: 0.0.4
Summary: A small example package
Home-page: https://github.com/pypa/sampleproject
Author: jigar2099
Author-email: jigarbhanderi@gmail.com
Project-URL: Bug Tracker, https://github.com/pypa/sampleproject/issues
Classifier: Programming Language :: Python :: 3
Classifier: License :: OSI Approved :: MIT License
Classifier: Operating System :: OS Independent
Requires-Python: >=3.6
License-File: LICENSE
